database_wrapper/__init__.py
database_wrapper/abc.py
database_wrapper/common.py
database_wrapper/config.py
database_wrapper/db_backend.py
database_wrapper/db_data_model.py
database_wrapper/db_introspector.py
database_wrapper/db_wrapper.py
database_wrapper/db_wrapper_async.py
database_wrapper/db_wrapper_mixin.py
database_wrapper/py.typed
database_wrapper/serialization.py
database_wrapper/utils/__init__.py
database_wrapper/utils/dataclass_addons.py
database_wrapper-0.2.23.dist-info/METADATA
database_wrapper-0.2.23.dist-info/WHEEL
database_wrapper-0.2.23.dist-info/top_level.txt
database_wrapper-0.2.23.dist-info/RECORD
