Metadata-Version: 2.4
Name: database_wrapper
Version: 0.2.23
Summary: A Different Approach to Database Wrappers in Python
Author-email: Gints Murans <gm@gm.lv>
License: GNU General Public License v3.0 (GPL-3.0)
Project-URL: Homepage, https://github.com/gintsmurans/py_database_wrapper
Project-URL: Documentation, https://github.com/gintsmurans/py_database_wrapper
Project-URL: Changes, https://github.com/gintsmurans/py_database_wrapper
Project-URL: Code, https://github.com/gintsmurans/py_database_wrapper
Project-URL: Issue Tracker, https://github.com/gintsmurans/py_database_wrapper/issues
Project-URL: Download, https://pypi.org/project/database_wrapper/
Keywords: database,wrapper,python,pgsql,mysql,mssql,sqlite,redis
Classifier: Development Status :: 4 - Beta
Classifier: Intended Audience :: Developers
Classifier: License :: OSI Approved :: GNU General Public License v3 (GPLv3)
Classifier: Operating System :: MacOS :: MacOS X
Classifier: Operating System :: Microsoft :: Windows
Classifier: Operating System :: POSIX
Classifier: Programming Language :: Python :: 3
Classifier: Programming Language :: Python :: 3.8
Classifier: Programming Language :: Python :: 3.9
Classifier: Programming Language :: Python :: 3.10
Classifier: Programming Language :: Python :: 3.11
Classifier: Programming Language :: Python :: 3.12
Classifier: Programming Language :: Python :: 3.13
Classifier: Programming Language :: Python :: Implementation :: CPython
Classifier: Programming Language :: Python :: Implementation :: PyPy
Classifier: Topic :: Database
Classifier: Topic :: Database :: Front-Ends
Classifier: Topic :: Software Development
Classifier: Topic :: Software Development :: Libraries :: Python Modules
Requires-Python: >=3.8
Provides-Extra: pgsql
Requires-Dist: database_wrapper_pgsql==0.2.23; extra == "pgsql"
Provides-Extra: mysql
Requires-Dist: database_wrapper_mysql==0.2.23; extra == "mysql"
Provides-Extra: mssql
Requires-Dist: database_wrapper_mssql==0.2.23; extra == "mssql"
Provides-Extra: sqlite
Requires-Dist: database_wrapper_sqlite==0.2.23; extra == "sqlite"
Provides-Extra: redis
Requires-Dist: database_wrapper_redis==0.2.23; extra == "redis"
Provides-Extra: all
Requires-Dist: database_wrapper[mssql,mysql,pgsql,redis,sqlite]; extra == "all"
Provides-Extra: dev
Requires-Dist: ast-comments>=1.1.2; extra == "dev"
Requires-Dist: codespell>=2.2; extra == "dev"
Requires-Dist: build>=1.2.1; extra == "dev"
Requires-Dist: pyrefly; extra == "dev"
Requires-Dist: ruff; extra == "dev"
Requires-Dist: types-setuptools>=61.0.0; extra == "dev"
Requires-Dist: types-pymssql>=2.1.0; extra == "dev"
Requires-Dist: types-mysqlclient>=2.2.0; extra == "dev"
Requires-Dist: psycopg[binary]>=3.2.0; extra == "dev"
Requires-Dist: psycopg[pool]>=3.2.0; extra == "dev"
Requires-Dist: mysqlclient>=2.2.2; extra == "dev"
Requires-Dist: pymssql>=2.2.10; extra == "dev"
